README.md
setup.py
lexis_bulk_api/__init__.py
lexis_bulk_api.egg-info/PKG-INFO
lexis_bulk_api.egg-info/SOURCES.txt
lexis_bulk_api.egg-info/dependency_links.txt
lexis_bulk_api.egg-info/entry_points.txt
lexis_bulk_api.egg-info/requires.txt
lexis_bulk_api.egg-info/top_level.txt