Metadata-Version: 1.0
Name: lexis-bulk-api
Version: 0.0.1
Summary: Visualize large image collections with WebGL
Home-page: https://github.com/yaledhlab/pix-plot
Author: Douglas Duhaime
Author-email: douglas.duhaime@gmail.com
License: MIT
Keywords: lexis-nexis,api,data,glam,vendor-data
Platform: UNKNOWN
